frechet_audio_distance/__init__.py
frechet_audio_distance/clap_score.py
frechet_audio_distance/fad.py
frechet_audio_distance/utils.py
frechet_audio_distance/models/__init__.py
frechet_audio_distance/models/pann.py
frechet_audio_distance/models/pytorch_utils.py
frechet_audio_distance-0.3.1.dist-info/LICENSE
frechet_audio_distance-0.3.1.dist-info/METADATA
frechet_audio_distance-0.3.1.dist-info/WHEEL
frechet_audio_distance-0.3.1.dist-info/top_level.txt
frechet_audio_distance-0.3.1.dist-info/RECORD
