Metadata-Version: 2.1
Name: frechet_audio_distance
Version: 0.3.1
Summary: A lightweight library of Frechet Audio Distance calculation.
Author-email: Hao Hao Tan <helloharry66@gmail.com>
License: MIT License
Project-URL: Homepage, https://github.com/gudgud96/frechet-audio-distance
Classifier: Programming Language :: Python :: 3
Classifier: License :: OSI Approved :: MIT License
Classifier: Operating System :: OS Independent
Requires-Python: >=3.7
License-File: LICENSE
Requires-Dist: numpy ==1.23.4
Requires-Dist: torch
Requires-Dist: scipy ==1.10.1
Requires-Dist: tqdm
Requires-Dist: soundfile
Requires-Dist: resampy
Requires-Dist: torchlibrosa
Requires-Dist: laion-clap
Requires-Dist: transformers <=4.30.2
Requires-Dist: torchaudio
Requires-Dist: encodec
